{"stats":{"minecraft:custom":{"minecraft:jump":2,"minecraft:open_chest":3,"minecraft:time_since_rest":2374,"minecraft:leave_game":1,"minecraft:damage_taken":280,"minecraft:sprint_one_cm":2034,"minecraft:play_time":2374,"minecraft:damage_absorbed":160,"minecraft:time_since_death":2374,"minecraft:walk_one_cm":2596,"minecraft:climb_one_cm":90,"minecraft:total_world_time":19083,"minecraft:damage_resisted":110,"minecraft:fly_one_cm":447},"minecraft:used":{"minecraft:suspicious_stew":2,"minecraft:enchanted_golden_apple":1}},"DataVersion":3465}